dataclass_exceptions/__init__.py
dataclass_exceptions/errors.py
dataclass_exceptions/types.py
dataclass_exceptions-0.1.1.dist-info/licenses/LICENSE.txt
dataclass_exceptions-0.1.1.dist-info/METADATA
dataclass_exceptions-0.1.1.dist-info/WHEEL
dataclass_exceptions-0.1.1.dist-info/top_level.txt
dataclass_exceptions-0.1.1.dist-info/RECORD
