Metadata-Version: 2.4
Name: dataclass-exceptions
Version: 0.1.1
Summary: A minimalist library for dataclass exceptions
Home-page: https://gitlab.com/Hares-Lab/libraries/dataclass-exceptions
Author: Peter Zaitcev / USSX-Hares
Maintainer: Peter Zaitcev / USSX-Hares
License: BSD 2-clause license
Classifier: Development Status :: 2 - Pre-Alpha
Classifier: Intended Audience :: Developers
Classifier: Natural Language :: English
Classifier: Operating System :: OS Independent
Classifier: Programming Language :: Python :: 3.12
Classifier: Programming Language :: Python :: 3.13
Classifier: Programming Language :: Python :: 3.14
Requires-Python: >=3.12
License-File: LICENSE.txt
Requires-Dist: dataclassabc~=0.0.15
Provides-Extra: test
Requires-Dist: wheel; extra == "test"
Requires-Dist: lxml; extra == "test"
Requires-Dist: unittest-xml-reporting; extra == "test"
Provides-Extra: all
Requires-Dist: wheel; extra == "all"
Requires-Dist: lxml; extra == "all"
Requires-Dist: unittest-xml-reporting; extra == "all"
Dynamic: author
Dynamic: classifier
Dynamic: description
Dynamic: description-content-type
Dynamic: home-page
Dynamic: license
Dynamic: license-file
Dynamic: maintainer
Dynamic: provides-extra
Dynamic: requires-dist
Dynamic: requires-python
Dynamic: summary
